[
    {
        "chunk": 76,
        "pos": 0,
        "terrain": "O",
        "features": "",
        "encounter": "",
        "history": []
    },
    {
        "chunk": 76,
        "pos": 1,
        "terrain": "O",
        "features": "",
        "encounter": "",
        "history": []
    },
    {
        "chunk": 76,
        "pos": 2,
        "terrain": "O",
        "features": "",
        "encounter": "Your journey is interrupted by runic ripple rift, with signs of manta protectors nearby.",
        "history": []
    },
    {
        "chunk": 76,
        "pos": 3,
        "terrain": "O",
        "features": "",
        "encounter": "",
        "history": []
    },
    {
        "chunk": 76,
        "pos": 4,
        "terrain": "O",
        "features": "",
        "encounter": "",
        "history": []
    },
    {
        "chunk": 76,
        "pos": 5,
        "terrain": "O",
        "features": "",
        "encounter": "",
        "history": []
    },
    {
        "chunk": 76,
        "pos": 6,
        "terrain": "H",
        "features": "Bare Zigzag",
        "encounter": "The surroundings hold (a) rusty bucket, which (are/is) said to be linked to hillfolk nomads.",
        "history": []
    },
    {
        "chunk": 76,
        "pos": 7,
        "terrain": "O",
        "features": "",
        "encounter": "",
        "history": []
    },
    {
        "chunk": 76,
        "pos": 8,
        "terrain": "O",
        "features": "",
        "encounter": "",
        "history": []
    },
    {
        "chunk": 76,
        "pos": 9,
        "terrain": "O",
        "features": "",
        "encounter": "",
        "history": []
    },
    {
        "chunk": 76,
        "pos": 10,
        "terrain": "O",
        "features": "",
        "encounter": "",
        "history": []
    },
    {
        "chunk": 76,
        "pos": 11,
        "terrain": "O",
        "features": "",
        "encounter": "",
        "history": []
    },
    {
        "chunk": 76,
        "pos": 12,
        "terrain": "O",
        "features": "",
        "encounter": "",
        "history": []
    },
    {
        "chunk": 76,
        "pos": 13,
        "terrain": "T",
        "features": "Phoenix Port",
        "encounter": "Legends tell of halfling cartographers that assist a cartographer in mapping the town amidst these lost property causing trip hazards.",
        "history": []
    },
    {
        "chunk": 76,
        "pos": 14,
        "terrain": "O",
        "features": "",
        "encounter": "",
        "history": []
    },
    {
        "chunk": 76,
        "pos": 15,
        "terrain": "O",
        "features": "",
        "encounter": "",
        "history": []
    },
    {
        "chunk": 76,
        "pos": 16,
        "terrain": "H",
        "features": "Nestled Plateau",
        "encounter": "You notice a(n) bracelet of terracotta animation that is oddly placed amongst the chamomile patches.",
        "history": []
    },
    {
        "chunk": 76,
        "pos": 17,
        "terrain": "O",
        "features": "",
        "encounter": "",
        "history": []
    },
    {
        "chunk": 76,
        "pos": 18,
        "terrain": "O",
        "features": "",
        "encounter": "",
        "history": []
    },
    {
        "chunk": 76,
        "pos": 19,
        "terrain": "O",
        "features": "",
        "encounter": "",
        "history": []
    },
    {
        "chunk": 76,
        "pos": 20,
        "terrain": "O",
        "features": "",
        "encounter": "",
        "history": []
    },
    {
        "chunk": 76,
        "pos": 21,
        "terrain": "O",
        "features": "",
        "encounter": "",
        "history": []
    },
    {
        "chunk": 76,
        "pos": 22,
        "terrain": "O",
        "features": "",
        "encounter": "",
        "history": []
    },
    {
        "chunk": 76,
        "pos": 23,
        "terrain": "H",
        "features": "Knoll-like Bank",
        "encounter": "You overhear tales of hillshade monks that constructing a shelter in this region.",
        "history": []
    },
    {
        "chunk": 76,
        "pos": 24,
        "terrain": "O",
        "features": "",
        "encounter": "",
        "history": []
    },
    {
        "chunk": 76,
        "pos": 25,
        "terrain": "H",
        "features": "Yearning Vista",
        "encounter": "Tales speak of rockslide serpents that are brewing drafts of transformation in these parts.",
        "history": []
    },
    {
        "chunk": 76,
        "pos": 26,
        "terrain": "H",
        "features": "Mounded Tor",
        "encounter": "You feel optimism as you spot a(n) bracelets of rockslide binding associated with burrow goblins.",
        "history": []
    },
    {
        "chunk": 76,
        "pos": 27,
        "terrain": "O",
        "features": "Raging Surf",
        "encounter": "",
        "history": []
    },
    {
        "chunk": 76,
        "pos": 28,
        "terrain": "O",
        "features": "",
        "encounter": "You're drawn to a(n) coral choker by a peculiar sense of dread.",
        "history": []
    },
    {
        "chunk": 76,
        "pos": 29,
        "terrain": "O",
        "features": "",
        "encounter": "",
        "history": []
    },
    {
        "chunk": 76,
        "pos": 30,
        "terrain": "O",
        "features": "",
        "encounter": "",
        "history": []
    },
    {
        "chunk": 76,
        "pos": 31,
        "terrain": "O",
        "features": "",
        "encounter": "",
        "history": []
    },
    {
        "chunk": 76,
        "pos": 32,
        "terrain": "H",
        "features": "Outstretched Vista",
        "encounter": "You find a(n) deck of many things found in a stone circle hidden among the starlight clover, which seems to be lost by hillcrest guardians.",
        "history": []
    },
    {
        "chunk": 76,
        "pos": 33,
        "terrain": "H",
        "features": "Quaint Rise",
        "encounter": "Your feel joy when you see phoenixes near a(n) bottle of stonebound spirits.",
        "history": []
    },
    {
        "chunk": 76,
        "pos": 34,
        "terrain": "P",
        "features": "Horizon-reaching Zephyr",
        "encounter": "A local speaks of sunrise seraphs that had sought to challenge the spirits in the tournament of echoes for a divine boon in this region.",
        "history": []
    },
    {
        "chunk": 76,
        "pos": 35,
        "terrain": "H",
        "features": "Lush Knoll",
        "encounter": "The path bears marks of hillshade ghosts and their interactions with a(n) sheep bell.",
        "history": []
    },
    {
        "chunk": 76,
        "pos": 36,
        "terrain": "H",
        "features": "Barren Escarpment",
        "encounter": "Legends tell of hillfolk mystic warriors that help a group of pilgrims reach a hilltop shrine amidst these magnetic anomalies.",
        "history": []
    },
    {
        "chunk": 76,
        "pos": 37,
        "terrain": "P",
        "features": "Limitless Upland",
        "encounter": "You overhear tales of prarie phoenix that are seeking the sanctum of the sun's serenade from old remnants of a circus tent.",
        "history": []
    },
    {
        "chunk": 76,
        "pos": 38,
        "terrain": "P",
        "features": "Xeric Barrens",
        "encounter": "Your journey is interrupted by a ground that's a shifting puzzle, with traces of field falconers nearby.",
        "history": []
    },
    {
        "chunk": 76,
        "pos": 39,
        "terrain": "H",
        "features": "Crested Terrace",
        "encounter": "Echoes of treant guardians resonate, accompanied by distinct hillside violets.",
        "history": []
    },
    {
        "chunk": 76,
        "pos": 40,
        "terrain": "O",
        "features": "",
        "encounter": "",
        "history": []
    },
    {
        "chunk": 76,
        "pos": 41,
        "terrain": "O",
        "features": "",
        "encounter": "",
        "history": []
    },
    {
        "chunk": 76,
        "pos": 42,
        "terrain": "H",
        "features": "Xerophilous Down",
        "encounter": "You see the old nymph's waterfall suggesting past activities of hillside harpists.",
        "history": []
    },
    {
        "chunk": 76,
        "pos": 43,
        "terrain": "H",
        "features": "Bare Brae",
        "encounter": "Echoes of hillside gryphon riders resonate, accompanied by distinct hilltop mint.",
        "history": []
    },
    {
        "chunk": 76,
        "pos": 44,
        "terrain": "F",
        "features": "Nurturing Paddock",
        "encounter": "You're warned of quicksand made of pixie dust ahead, where bats often are crawling slowly.",
        "history": []
    },
    {
        "chunk": 76,
        "pos": 45,
        "terrain": "H",
        "features": "Eroded Down",
        "encounter": "Whispers suggest ridge runner enchanters are seeking the heart of the hill old stone well.",
        "history": []
    },
    {
        "chunk": 76,
        "pos": 46,
        "terrain": "H",
        "features": "Sloping Yawn",
        "encounter": "As you proceed, hillside griffin riders suddenly chasing the trails of comets from behind a(n) dagger of venom found in a hill serpent's nest.",
        "history": []
    },
    {
        "chunk": 76,
        "pos": 47,
        "terrain": "P",
        "features": "Open Basin",
        "encounter": "You're warned of a sudden and mysterious light from the ground ahead, where tallgrass titans often are training in the ways of the land.",
        "history": []
    },
    {
        "chunk": 76,
        "pos": 48,
        "terrain": "O",
        "features": "",
        "encounter": "",
        "history": []
    },
    {
        "chunk": 76,
        "pos": 49,
        "terrain": "O",
        "features": "Teeming Chasm",
        "encounter": "",
        "history": []
    },
    {
        "chunk": 76,
        "pos": 50,
        "terrain": "O",
        "features": "",
        "encounter": "",
        "history": []
    },
    {
        "chunk": 76,
        "pos": 51,
        "terrain": "O",
        "features": "",
        "encounter": "",
        "history": []
    },
    {
        "chunk": 76,
        "pos": 52,
        "terrain": "H",
        "features": "Wooded Heath",
        "encounter": "The chamomile patches rustles as moss elementals are battling shadowy apparitions behind them.",
        "history": []
    },
    {
        "chunk": 76,
        "pos": 53,
        "terrain": "H",
        "features": "Misty Bank",
        "encounter": "A strong scent of freshly tilled earth suggests recent activity by terrace gnome mechanics.",
        "history": []
    },
    {
        "chunk": 76,
        "pos": 54,
        "terrain": "P",
        "features": "Prairie Chaparral",
        "encounter": "A sudden the scent of a night's hunt alerts you to the presence of dancing deer.",
        "history": []
    },
    {
        "chunk": 76,
        "pos": 55,
        "terrain": "H",
        "features": "Undulating Ridge",
        "encounter": "The boulder fields ahead are said to be the work of burrowed basilisks that are studying the stars.",
        "history": []
    },
    {
        "chunk": 76,
        "pos": 56,
        "terrain": "H",
        "features": "Tranquil Ridge",
        "encounter": "A sense of respect grips you as you discover a(n) cracked bowl linked to rocktop elementals.",
        "history": []
    },
    {
        "chunk": 76,
        "pos": 57,
        "terrain": "P",
        "features": "Hallowed Zephyr",
        "encounter": "The dense sunflare shrub seems to whisper tales of tallgrass troubadours and their aid a prairie oracle in deciphering a prophecy.",
        "history": []
    },
    {
        "chunk": 76,
        "pos": 58,
        "terrain": "P",
        "features": "Vibrant Expanse",
        "encounter": "The path reveals yodeling youths that seem to be seeking the realm where the winds are born in order to challenge the echoing beast, a creature of sound and fury.",
        "history": []
    },
    {
        "chunk": 76,
        "pos": 59,
        "terrain": "O",
        "features": "",
        "encounter": "",
        "history": []
    },
    {
        "chunk": 76,
        "pos": 60,
        "terrain": "O",
        "features": "",
        "encounter": "",
        "history": []
    },
    {
        "chunk": 76,
        "pos": 61,
        "terrain": "O",
        "features": "",
        "encounter": "",
        "history": []
    },
    {
        "chunk": 76,
        "pos": 62,
        "terrain": "H",
        "features": "Lofty Upland",
        "encounter": "You hear the distant sound of bouldershade wolves stretching their wings.",
        "history": []
    },
    {
        "chunk": 76,
        "pos": 63,
        "terrain": "H",
        "features": "Eroded Upland",
        "encounter": "Ancient stories speak of terrace gnome tinkerers whos objective was to retrieve a magical horn said to be in a hillside grove here.",
        "history": []
    },
    {
        "chunk": 76,
        "pos": 64,
        "terrain": "F",
        "features": "Glistening Expanse",
        "encounter": "A local offers you a quest to help a ranger track down a poacher involving giant porcupines.",
        "history": []
    },
    {
        "chunk": 76,
        "pos": 65,
        "terrain": "H",
        "features": "Wavy Butte",
        "encounter": "You're drawn to a(n) rusty chain by an overwhelming sense of reflection.",
        "history": []
    },
    {
        "chunk": 76,
        "pos": 66,
        "terrain": "H",
        "features": "Rocky Eminence",
        "encounter": "As you proceed, rockspire elementals suddenly transforming rocks into living creatures from behind a(n) instrument of the bards echoing hill songs.",
        "history": []
    },
    {
        "chunk": 76,
        "pos": 67,
        "terrain": "P",
        "features": "Expansive Outwash",
        "encounter": "The dense pasque flower seems to whisper tales of mystical meerkats and their seek the cavern of echoing dreams, a place of visions.",
        "history": []
    },
    {
        "chunk": 76,
        "pos": 68,
        "terrain": "H",
        "features": "Hazy Tor",
        "encounter": "Echoes of stonebound specters resonate, accompanied by distinct blossoming cherry trees.",
        "history": []
    },
    {
        "chunk": 76,
        "pos": 69,
        "terrain": "O",
        "features": "",
        "encounter": "",
        "history": []
    },
    {
        "chunk": 76,
        "pos": 70,
        "terrain": "O",
        "features": "",
        "encounter": "",
        "history": []
    },
    {
        "chunk": 76,
        "pos": 71,
        "terrain": "O",
        "features": "",
        "encounter": "",
        "history": []
    },
    {
        "chunk": 76,
        "pos": 72,
        "terrain": "H",
        "features": "Xerophilous Butte",
        "encounter": "Beneath a rock overhang, you hear boulder beast enchanters engaging in a dance of the constellations, accompanied by freshly fallen rain.",
        "history": []
    },
    {
        "chunk": 76,
        "pos": 73,
        "terrain": "H",
        "features": "Isolated Decline",
        "encounter": "Behind a cluster of wild rose bushes, you sense the presence of harpies.",
        "history": []
    },
    {
        "chunk": 76,
        "pos": 74,
        "terrain": "P",
        "features": "Quiescent Dale",
        "encounter": "The surroundings hold (a) mystical meteorite fragment, which (are/is) said to be linked to earth elementals.",
        "history": []
    },
    {
        "chunk": 76,
        "pos": 75,
        "terrain": "H",
        "features": "Towering Crest",
        "encounter": "Your journey is interrupted by blocked pathways, with signs of stone sentinel archers nearby.",
        "history": []
    },
    {
        "chunk": 76,
        "pos": 76,
        "terrain": "H",
        "features": "Thicketed Embankment",
        "encounter": "A sense of optimism washes over you as hillfolk guardians are scouting the area for dangers nearby.",
        "history": []
    },
    {
        "chunk": 76,
        "pos": 77,
        "terrain": "P",
        "features": "Endless Tableland",
        "encounter": "The ground is littered with the distant roar of a creature no one has ever seen, and you can smell freshly turned earth coming from a nearby inside the shade of a cloud shaped like a beast.",
        "history": []
    },
    {
        "chunk": 76,
        "pos": 78,
        "terrain": "O",
        "features": "",
        "encounter": "",
        "history": []
    },
    {
        "chunk": 76,
        "pos": 79,
        "terrain": "O",
        "features": "",
        "encounter": "",
        "history": []
    },
    {
        "chunk": 76,
        "pos": 80,
        "terrain": "O",
        "features": "",
        "encounter": "",
        "history": []
    },
    {
        "chunk": 76,
        "pos": 81,
        "terrain": "O",
        "features": "",
        "encounter": "",
        "history": []
    },
    {
        "chunk": 76,
        "pos": 82,
        "terrain": "O",
        "features": "",
        "encounter": "A strong scent of sail's canvas leads you towards moray eels.",
        "history": []
    },
    {
        "chunk": 76,
        "pos": 83,
        "terrain": "H",
        "features": "Secluded Embankment",
        "encounter": "Your journey is interrupted by fields where stars shine even during the day, with signs of ridge runner scouts nearby.",
        "history": []
    },
    {
        "chunk": 76,
        "pos": 84,
        "terrain": "O",
        "features": "",
        "encounter": "",
        "history": []
    },
    {
        "chunk": 76,
        "pos": 85,
        "terrain": "H",
        "features": "Wooded Crag",
        "encounter": "A sense of fulfillment washes over you as stone whisperers are holding a symposium with other realms nearby.",
        "history": []
    },
    {
        "chunk": 76,
        "pos": 86,
        "terrain": "H",
        "features": "Rugged Tor",
        "encounter": "A strong scent of ripening berries suggests recent activity by terrace phoenix riders.",
        "history": []
    },
    {
        "chunk": 76,
        "pos": 87,
        "terrain": "O",
        "features": "",
        "encounter": "",
        "history": []
    },
    {
        "chunk": 76,
        "pos": 88,
        "terrain": "O",
        "features": "",
        "encounter": "",
        "history": []
    },
    {
        "chunk": 76,
        "pos": 89,
        "terrain": "O",
        "features": "Glistening Islet",
        "encounter": "",
        "history": []
    },
    {
        "chunk": 76,
        "pos": 90,
        "terrain": "O",
        "features": "",
        "encounter": "",
        "history": []
    },
    {
        "chunk": 76,
        "pos": 91,
        "terrain": "O",
        "features": "",
        "encounter": "",
        "history": []
    },
    {
        "chunk": 76,
        "pos": 92,
        "terrain": "O",
        "features": "",
        "encounter": "",
        "history": []
    },
    {
        "chunk": 76,
        "pos": 93,
        "terrain": "O",
        "features": "",
        "encounter": "",
        "history": []
    },
    {
        "chunk": 76,
        "pos": 94,
        "terrain": "O",
        "features": "",
        "encounter": "",
        "history": []
    },
    {
        "chunk": 76,
        "pos": 95,
        "terrain": "O",
        "features": "Hushed Bight",
        "encounter": "",
        "history": []
    },
    {
        "chunk": 76,
        "pos": 96,
        "terrain": "H",
        "features": "Hazy Summit",
        "encounter": "You're filled with satisfaction upon discovering a(n) dagger of stone splitting linked to hillside satyrs.",
        "history": []
    },
    {
        "chunk": 76,
        "pos": 97,
        "terrain": "O",
        "features": "",
        "encounter": "",
        "history": []
    },
    {
        "chunk": 76,
        "pos": 98,
        "terrain": "O",
        "features": "Expansive Bight",
        "encounter": "",
        "history": []
    },
    {
        "chunk": 76,
        "pos": 99,
        "terrain": "O",
        "features": "Misty Eddy",
        "encounter": "",
        "history": []
    }
]