[
    {
        "pos": 0,
        "terrain": "O",
        "features": "",
        "encounter": ""
    },
    {
        "pos": 1,
        "terrain": "O",
        "features": "",
        "encounter": ""
    },
    {
        "pos": 2,
        "terrain": "O",
        "features": "",
        "encounter": ""
    },
    {
        "pos": 3,
        "terrain": "O",
        "features": "",
        "encounter": ""
    },
    {
        "pos": 4,
        "terrain": "O",
        "features": "",
        "encounter": ""
    },
    {
        "pos": 5,
        "terrain": "O",
        "features": "",
        "encounter": ""
    },
    {
        "pos": 6,
        "terrain": "O",
        "features": "",
        "encounter": ""
    },
    {
        "pos": 7,
        "terrain": "O",
        "features": "",
        "encounter": ""
    },
    {
        "pos": 8,
        "terrain": "O",
        "features": "",
        "encounter": ""
    },
    {
        "pos": 9,
        "terrain": "O",
        "features": "",
        "encounter": ""
    },
    {
        "pos": 10,
        "terrain": "O",
        "features": "",
        "encounter": ""
    },
    {
        "pos": 11,
        "terrain": "O",
        "features": "",
        "encounter": ""
    },
    {
        "pos": 12,
        "terrain": "O",
        "features": "",
        "encounter": ""
    },
    {
        "pos": 13,
        "terrain": "O",
        "features": "",
        "encounter": ""
    },
    {
        "pos": 14,
        "terrain": "O",
        "features": "",
        "encounter": ""
    },
    {
        "pos": 15,
        "terrain": "O",
        "features": "",
        "encounter": ""
    },
    {
        "pos": 16,
        "terrain": "O",
        "features": "Abyssal Plateau",
        "encounter": ""
    },
    {
        "pos": 17,
        "terrain": "O",
        "features": "",
        "encounter": ""
    },
    {
        "pos": 18,
        "terrain": "O",
        "features": "",
        "encounter": ""
    },
    {
        "pos": 19,
        "terrain": "O",
        "features": "",
        "encounter": ""
    },
    {
        "pos": 20,
        "terrain": "O",
        "features": "",
        "encounter": "The kelp forests rustles, revealing turtle island shamans that are creating elaborate maps of uncharted waters."
    },
    {
        "pos": 21,
        "terrain": "O",
        "features": "",
        "encounter": "You hear sizzling of saltwater on hot volcanic rocks coming from a secret merfolk concert hall hidden in a cave."
    },
    {
        "pos": 22,
        "terrain": "O",
        "features": "",
        "encounter": "The ground trembles slightly, and clattering of seashells in the tide grow louder. It seems sea witches are on the move."
    },
    {
        "pos": 23,
        "terrain": "O",
        "features": "",
        "encounter": ""
    },
    {
        "pos": 24,
        "terrain": "O",
        "features": "",
        "encounter": "Hidden among giant underwater mushrooms, you spot a seafarer's journal filled with tales of adventure glinting in the sunlight."
    },
    {
        "pos": 25,
        "terrain": "O",
        "features": "",
        "encounter": ""
    },
    {
        "pos": 26,
        "terrain": "O",
        "features": "",
        "encounter": ""
    },
    {
        "pos": 27,
        "terrain": "O",
        "features": "",
        "encounter": ""
    },
    {
        "pos": 28,
        "terrain": "O",
        "features": "",
        "encounter": ""
    },
    {
        "pos": 29,
        "terrain": "O",
        "features": "",
        "encounter": ""
    },
    {
        "pos": 30,
        "terrain": "O",
        "features": "",
        "encounter": ""
    },
    {
        "pos": 31,
        "terrain": "O",
        "features": "Boundless Flats",
        "encounter": ""
    },
    {
        "pos": 32,
        "terrain": "O",
        "features": "",
        "encounter": "Your journey leads you to a a ship-eating whirlpool known as the 'ship swallower'. As you approach, underwater miners healing wounded sea creatures."
    },
    {
        "pos": 33,
        "terrain": "O",
        "features": "",
        "encounter": ""
    },
    {
        "pos": 34,
        "terrain": "O",
        "features": "",
        "encounter": ""
    },
    {
        "pos": 35,
        "terrain": "O",
        "features": "",
        "encounter": ""
    },
    {
        "pos": 36,
        "terrain": "O",
        "features": "",
        "encounter": "A sudden murmuring of merfolk singing in harmony breaks the silence, making the nearby tube worms near hydrothermal vents quiver."
    },
    {
        "pos": 37,
        "terrain": "O",
        "features": "",
        "encounter": ""
    },
    {
        "pos": 38,
        "terrain": "O",
        "features": "",
        "encounter": ""
    },
    {
        "pos": 39,
        "terrain": "O",
        "features": "",
        "encounter": ""
    },
    {
        "pos": 40,
        "terrain": "O",
        "features": "",
        "encounter": ""
    },
    {
        "pos": 41,
        "terrain": "O",
        "features": "",
        "encounter": ""
    },
    {
        "pos": 42,
        "terrain": "O",
        "features": "",
        "encounter": ""
    },
    {
        "pos": 43,
        "terrain": "O",
        "features": "",
        "encounter": ""
    },
    {
        "pos": 44,
        "terrain": "O",
        "features": "",
        "encounter": "Trails of a waterlogged chest with its lid ajar wind through the caulerpa seaweed, revealing the past actions of oceanic alchemists."
    },
    {
        "pos": 45,
        "terrain": "O",
        "features": "Azure Whirlpool",
        "encounter": ""
    },
    {
        "pos": 46,
        "terrain": "O",
        "features": "",
        "encounter": "Strange the remnants of a sunken merchant ship's cargo lie scattered, painting a tale of turtle island shamans that convincing a shipwrecked sailor to join their crew."
    },
    {
        "pos": 47,
        "terrain": "O",
        "features": "",
        "encounter": "Among the dense sponge colonies, you discover a chest of mystical sea herbs and remedies. You can't shake the feeling of anxiety."
    },
    {
        "pos": 48,
        "terrain": "O",
        "features": "",
        "encounter": ""
    },
    {
        "pos": 49,
        "terrain": "O",
        "features": "Majestic Passage",
        "encounter": ""
    },
    {
        "pos": 50,
        "terrain": "O",
        "features": "Immeasurable Bay",
        "encounter": ""
    },
    {
        "pos": 51,
        "terrain": "O",
        "features": "",
        "encounter": ""
    },
    {
        "pos": 52,
        "terrain": "O",
        "features": "",
        "encounter": ""
    },
    {
        "pos": 53,
        "terrain": "O",
        "features": "",
        "encounter": ""
    },
    {
        "pos": 54,
        "terrain": "O",
        "features": "",
        "encounter": ""
    },
    {
        "pos": 55,
        "terrain": "O",
        "features": "",
        "encounter": ""
    },
    {
        "pos": 56,
        "terrain": "O",
        "features": "",
        "encounter": ""
    },
    {
        "pos": 57,
        "terrain": "O",
        "features": "",
        "encounter": ""
    },
    {
        "pos": 58,
        "terrain": "O",
        "features": "",
        "encounter": ""
    },
    {
        "pos": 59,
        "terrain": "O",
        "features": "",
        "encounter": ""
    },
    {
        "pos": 60,
        "terrain": "O",
        "features": "",
        "encounter": ""
    },
    {
        "pos": 61,
        "terrain": "O",
        "features": "",
        "encounter": ""
    },
    {
        "pos": 62,
        "terrain": "O",
        "features": "",
        "encounter": ""
    },
    {
        "pos": 63,
        "terrain": "O",
        "features": "",
        "encounter": ""
    },
    {
        "pos": 64,
        "terrain": "O",
        "features": "",
        "encounter": ""
    },
    {
        "pos": 65,
        "terrain": "O",
        "features": "",
        "encounter": ""
    },
    {
        "pos": 66,
        "terrain": "O",
        "features": "",
        "encounter": ""
    },
    {
        "pos": 67,
        "terrain": "O",
        "features": "",
        "encounter": ""
    },
    {
        "pos": 68,
        "terrain": "O",
        "features": "",
        "encounter": ""
    },
    {
        "pos": 69,
        "terrain": "O",
        "features": "",
        "encounter": ""
    },
    {
        "pos": 70,
        "terrain": "O",
        "features": "",
        "encounter": ""
    },
    {
        "pos": 71,
        "terrain": "O",
        "features": "",
        "encounter": ""
    },
    {
        "pos": 72,
        "terrain": "O",
        "features": "",
        "encounter": ""
    },
    {
        "pos": 73,
        "terrain": "O",
        "features": "",
        "encounter": ""
    },
    {
        "pos": 74,
        "terrain": "O",
        "features": "",
        "encounter": ""
    },
    {
        "pos": 75,
        "terrain": "O",
        "features": "",
        "encounter": ""
    },
    {
        "pos": 76,
        "terrain": "O",
        "features": "",
        "encounter": ""
    },
    {
        "pos": 77,
        "terrain": "O",
        "features": "",
        "encounter": ""
    },
    {
        "pos": 78,
        "terrain": "O",
        "features": "",
        "encounter": ""
    },
    {
        "pos": 79,
        "terrain": "O",
        "features": "",
        "encounter": ""
    },
    {
        "pos": 80,
        "terrain": "O",
        "features": "",
        "encounter": ""
    },
    {
        "pos": 81,
        "terrain": "O",
        "features": "",
        "encounter": ""
    },
    {
        "pos": 82,
        "terrain": "O",
        "features": "",
        "encounter": ""
    },
    {
        "pos": 83,
        "terrain": "O",
        "features": "",
        "encounter": ""
    },
    {
        "pos": 84,
        "terrain": "O",
        "features": "",
        "encounter": ""
    },
    {
        "pos": 85,
        "terrain": "O",
        "features": "",
        "encounter": ""
    },
    {
        "pos": 86,
        "terrain": "O",
        "features": "",
        "encounter": ""
    },
    {
        "pos": 87,
        "terrain": "O",
        "features": "",
        "encounter": ""
    },
    {
        "pos": 88,
        "terrain": "O",
        "features": "",
        "encounter": ""
    },
    {
        "pos": 89,
        "terrain": "O",
        "features": "",
        "encounter": ""
    },
    {
        "pos": 90,
        "terrain": "O",
        "features": "",
        "encounter": ""
    },
    {
        "pos": 91,
        "terrain": "O",
        "features": "",
        "encounter": ""
    },
    {
        "pos": 92,
        "terrain": "O",
        "features": "",
        "encounter": ""
    },
    {
        "pos": 93,
        "terrain": "O",
        "features": "",
        "encounter": ""
    },
    {
        "pos": 94,
        "terrain": "O",
        "features": "",
        "encounter": ""
    },
    {
        "pos": 95,
        "terrain": "O",
        "features": "",
        "encounter": ""
    },
    {
        "pos": 96,
        "terrain": "O",
        "features": "",
        "encounter": ""
    },
    {
        "pos": 97,
        "terrain": "O",
        "features": "",
        "encounter": ""
    },
    {
        "pos": 98,
        "terrain": "O",
        "features": "",
        "encounter": "The way forward is blocked by a thick forest of kelp that entangles ships, but you notice a submerged sea cave filled with bioluminescent creatures that might lead around it."
    },
    {
        "pos": 99,
        "terrain": "O",
        "features": "",
        "encounter": ""
    }
]