[
    {
        "pos": 0,
        "terrain": "O",
        "features": "",
        "encounter": "A sudden chattering of crabs on a rocky shore breaks the silence, making the nearby bubbling hot seawater vents quiver."
    },
    {
        "pos": 1,
        "terrain": "O",
        "features": "",
        "encounter": "A sudden gust brings with it crisp, ocean-scented laundry on a line. You spot ship-eating barnacles that seem to be forging alliances with other oceanic races."
    },
    {
        "pos": 2,
        "terrain": "O",
        "features": "",
        "encounter": "You feel panic as gurgling of a freshwater stream meeting the ocean echo in the distance. Perhaps it's a sign of what's to come."
    },
    {
        "pos": 3,
        "terrain": "O",
        "features": "",
        "encounter": ""
    },
    {
        "pos": 4,
        "terrain": "O",
        "features": "Endless Depression",
        "encounter": ""
    },
    {
        "pos": 5,
        "terrain": "O",
        "features": "",
        "encounter": ""
    },
    {
        "pos": 6,
        "terrain": "O",
        "features": "",
        "encounter": ""
    },
    {
        "pos": 7,
        "terrain": "O",
        "features": "",
        "encounter": ""
    },
    {
        "pos": 8,
        "terrain": "O",
        "features": "",
        "encounter": ""
    },
    {
        "pos": 9,
        "terrain": "O",
        "features": "",
        "encounter": ""
    },
    {
        "pos": 10,
        "terrain": "O",
        "features": "",
        "encounter": ""
    },
    {
        "pos": 11,
        "terrain": "O",
        "features": "",
        "encounter": ""
    },
    {
        "pos": 12,
        "terrain": "O",
        "features": "",
        "encounter": ""
    },
    {
        "pos": 13,
        "terrain": "O",
        "features": "",
        "encounter": ""
    },
    {
        "pos": 14,
        "terrain": "O",
        "features": "",
        "encounter": ""
    },
    {
        "pos": 15,
        "terrain": "O",
        "features": "Soothing Undercurrent",
        "encounter": ""
    },
    {
        "pos": 16,
        "terrain": "O",
        "features": "",
        "encounter": "A path surrounded by kelp forests leads to a clearing with a sunken chest with its lock rusted shut, indicating storm giants have been here."
    },
    {
        "pos": 17,
        "terrain": "O",
        "features": "Nautical Trough",
        "encounter": "Trails of a sunken rowboat with a hole in its hull wind through the gorgonian sea fans, revealing the past actions of water elementals."
    },
    {
        "pos": 18,
        "terrain": "O",
        "features": "Timeless Pinnacle",
        "encounter": "The air is filled with the smell of tangy scent of salt spray. You feel a sense of grief."
    },
    {
        "pos": 19,
        "terrain": "O",
        "features": "",
        "encounter": ""
    },
    {
        "pos": 20,
        "terrain": "O",
        "features": "",
        "encounter": ""
    },
    {
        "pos": 21,
        "terrain": "O",
        "features": "",
        "encounter": ""
    },
    {
        "pos": 22,
        "terrain": "O",
        "features": "",
        "encounter": ""
    },
    {
        "pos": 23,
        "terrain": "O",
        "features": "",
        "encounter": ""
    },
    {
        "pos": 24,
        "terrain": "O",
        "features": "",
        "encounter": ""
    },
    {
        "pos": 25,
        "terrain": "O",
        "features": "",
        "encounter": ""
    },
    {
        "pos": 26,
        "terrain": "O",
        "features": "",
        "encounter": "The whisper of buzzing of bioluminescent creatures in the depths is accompanied by the distinct aroma of musty odor of a hidden sea cave. It seems sunken treasure guardians are involved in engaging in a sea battle with rival pirates."
    },
    {
        "pos": 27,
        "terrain": "O",
        "features": "",
        "encounter": ""
    },
    {
        "pos": 28,
        "terrain": "O",
        "features": "",
        "encounter": "You feel an overwhelming sense of anxiety as you tread upon a tattered, waterlogged map of uncharted waters, hinting at a tale of giant clams."
    },
    {
        "pos": 29,
        "terrain": "O",
        "features": "",
        "encounter": ""
    },
    {
        "pos": 30,
        "terrain": "O",
        "features": "Grand Whirlpool",
        "encounter": "You stumble upon a broken ship's mast jutting out of the water indicating past battles."
    },
    {
        "pos": 31,
        "terrain": "O",
        "features": "Inviting Delta",
        "encounter": "With help a stranded sea serpent find its way back to the open sea. On your mind, the sudden appearance of a colony of hostile merfolk guarding their territory accompanied by clattering of seashells in the tide becomes a challenging diversion."
    },
    {
        "pos": 32,
        "terrain": "O",
        "features": "",
        "encounter": "You stumble upon a torn and faded pirate's treasure map indicating past battles."
    },
    {
        "pos": 33,
        "terrain": "O",
        "features": "",
        "encounter": ""
    },
    {
        "pos": 34,
        "terrain": "O",
        "features": "",
        "encounter": ""
    },
    {
        "pos": 35,
        "terrain": "O",
        "features": "",
        "encounter": ""
    },
    {
        "pos": 36,
        "terrain": "O",
        "features": "",
        "encounter": ""
    },
    {
        "pos": 37,
        "terrain": "O",
        "features": "",
        "encounter": ""
    },
    {
        "pos": 38,
        "terrain": "O",
        "features": "",
        "encounter": "You stumble upon a scene where floating market traders are engaged in performing a ritual to calm a storm around a collection of seashells with hidden messages, seemingly crucial for guide a group of scholars on a research expedition to the deep ocean.."
    },
    {
        "pos": 39,
        "terrain": "O",
        "features": "",
        "encounter": ""
    },
    {
        "pos": 40,
        "terrain": "O",
        "features": "Sunlit Marina",
        "encounter": ""
    },
    {
        "pos": 41,
        "terrain": "O",
        "features": "",
        "encounter": ""
    },
    {
        "pos": 42,
        "terrain": "O",
        "features": "",
        "encounter": ""
    },
    {
        "pos": 43,
        "terrain": "O",
        "features": "",
        "encounter": "You stumble upon an abandoned lifeboat adrift on the waves indicating past battles."
    },
    {
        "pos": 44,
        "terrain": "O",
        "features": "",
        "encounter": ""
    },
    {
        "pos": 45,
        "terrain": "O",
        "features": "",
        "encounter": ""
    },
    {
        "pos": 46,
        "terrain": "O",
        "features": "",
        "encounter": ""
    },
    {
        "pos": 47,
        "terrain": "O",
        "features": "",
        "encounter": ""
    },
    {
        "pos": 48,
        "terrain": "O",
        "features": "Sparkling Fjord",
        "encounter": ""
    },
    {
        "pos": 49,
        "terrain": "O",
        "features": "",
        "encounter": ""
    },
    {
        "pos": 50,
        "terrain": "O",
        "features": "",
        "encounter": ""
    },
    {
        "pos": 51,
        "terrain": "O",
        "features": "",
        "encounter": ""
    },
    {
        "pos": 52,
        "terrain": "O",
        "features": "",
        "encounter": ""
    },
    {
        "pos": 53,
        "terrain": "O",
        "features": "",
        "encounter": ""
    },
    {
        "pos": 54,
        "terrain": "O",
        "features": "",
        "encounter": ""
    },
    {
        "pos": 55,
        "terrain": "O",
        "features": "",
        "encounter": ""
    },
    {
        "pos": 56,
        "terrain": "O",
        "features": "",
        "encounter": ""
    },
    {
        "pos": 57,
        "terrain": "O",
        "features": "",
        "encounter": ""
    },
    {
        "pos": 58,
        "terrain": "O",
        "features": "",
        "encounter": ""
    },
    {
        "pos": 59,
        "terrain": "O",
        "features": "",
        "encounter": ""
    },
    {
        "pos": 60,
        "terrain": "O",
        "features": "",
        "encounter": ""
    },
    {
        "pos": 61,
        "terrain": "O",
        "features": "",
        "encounter": ""
    },
    {
        "pos": 62,
        "terrain": "O",
        "features": "",
        "encounter": ""
    },
    {
        "pos": 63,
        "terrain": "O",
        "features": "Crystal-clear Jetty",
        "encounter": ""
    },
    {
        "pos": 64,
        "terrain": "O",
        "features": "",
        "encounter": ""
    },
    {
        "pos": 65,
        "terrain": "O",
        "features": "",
        "encounter": ""
    },
    {
        "pos": 66,
        "terrain": "O",
        "features": "Dazzling Harbor",
        "encounter": "Lighthouse guardians gives you a quest to solve the mystery of a cursed shipwreck and its crew's fate.In your path lies a ghostly lantern that wards off spirits surrounded by sea palm kelp."
    },
    {
        "pos": 67,
        "terrain": "O",
        "features": "",
        "encounter": "With rescue a group of trapped sailors from a sinking ship. On your mind, the sudden appearance of a massive, floating tree trunk in the ship's path accompanied by sloshing of water in a mermaid's bathtub becomes a challenging diversion."
    },
    {
        "pos": 68,
        "terrain": "O",
        "features": "",
        "encounter": ""
    },
    {
        "pos": 69,
        "terrain": "O",
        "features": "",
        "encounter": ""
    },
    {
        "pos": 70,
        "terrain": "O",
        "features": "",
        "encounter": ""
    },
    {
        "pos": 71,
        "terrain": "O",
        "features": "",
        "encounter": ""
    },
    {
        "pos": 72,
        "terrain": "O",
        "features": "",
        "encounter": ""
    },
    {
        "pos": 73,
        "terrain": "O",
        "features": "",
        "encounter": ""
    },
    {
        "pos": 74,
        "terrain": "O",
        "features": "",
        "encounter": ""
    },
    {
        "pos": 75,
        "terrain": "O",
        "features": "",
        "encounter": ""
    },
    {
        "pos": 76,
        "terrain": "O",
        "features": "",
        "encounter": "You feel guilt as rattling of pebbles in the surf echo in the distance. Perhaps it's a sign of what's to come."
    },
    {
        "pos": 77,
        "terrain": "O",
        "features": "",
        "encounter": ""
    },
    {
        "pos": 78,
        "terrain": "O",
        "features": "",
        "encounter": ""
    },
    {
        "pos": 79,
        "terrain": "O",
        "features": "",
        "encounter": ""
    },
    {
        "pos": 80,
        "terrain": "O",
        "features": "",
        "encounter": ""
    },
    {
        "pos": 81,
        "terrain": "O",
        "features": "",
        "encounter": ""
    },
    {
        "pos": 82,
        "terrain": "O",
        "features": "",
        "encounter": ""
    },
    {
        "pos": 83,
        "terrain": "O",
        "features": "",
        "encounter": ""
    },
    {
        "pos": 84,
        "terrain": "O",
        "features": "",
        "encounter": ""
    },
    {
        "pos": 85,
        "terrain": "O",
        "features": "",
        "encounter": "Trails of a beached rowboat with a broken oar wind through the gorgonian sea fans, revealing the past actions of seafaring druids."
    },
    {
        "pos": 86,
        "terrain": "O",
        "features": "",
        "encounter": ""
    },
    {
        "pos": 87,
        "terrain": "O",
        "features": "",
        "encounter": ""
    },
    {
        "pos": 88,
        "terrain": "O",
        "features": "Nautical Inlet",
        "encounter": ""
    },
    {
        "pos": 89,
        "terrain": "O",
        "features": "Reflective Tidal Pool",
        "encounter": ""
    },
    {
        "pos": 90,
        "terrain": "O",
        "features": "Crystal-clear Deep",
        "encounter": ""
    },
    {
        "pos": 91,
        "terrain": "O",
        "features": "",
        "encounter": ""
    },
    {
        "pos": 92,
        "terrain": "O",
        "features": "",
        "encounter": "A trail of a damaged sextant with a cracked lens suggests that ghost ships have passed through here on a quest to explore an underwater cave system to find a valuable artifact.."
    },
    {
        "pos": 93,
        "terrain": "O",
        "features": "",
        "encounter": ""
    },
    {
        "pos": 94,
        "terrain": "O",
        "features": "",
        "encounter": ""
    },
    {
        "pos": 95,
        "terrain": "O",
        "features": "",
        "encounter": ""
    },
    {
        "pos": 96,
        "terrain": "O",
        "features": "",
        "encounter": ""
    },
    {
        "pos": 97,
        "terrain": "O",
        "features": "",
        "encounter": ""
    },
    {
        "pos": 98,
        "terrain": "O",
        "features": "",
        "encounter": ""
    },
    {
        "pos": 99,
        "terrain": "O",
        "features": "",
        "encounter": ""
    }
]