[
    {
        "pos": 0,
        "terrain": "O",
        "features": "Calm ['Rift']",
        "encounter": ""
    },
    {
        "pos": 1,
        "terrain": "O",
        "features": "",
        "encounter": ""
    },
    {
        "pos": 2,
        "terrain": "O",
        "features": "",
        "encounter": ""
    },
    {
        "pos": 3,
        "terrain": "O",
        "features": "",
        "encounter": ""
    },
    {
        "pos": 4,
        "terrain": "O",
        "features": "",
        "encounter": ""
    },
    {
        "pos": 5,
        "terrain": "O",
        "features": "",
        "encounter": ""
    },
    {
        "pos": 6,
        "terrain": "O",
        "features": "",
        "encounter": ""
    },
    {
        "pos": 7,
        "terrain": "O",
        "features": "",
        "encounter": ""
    },
    {
        "pos": 8,
        "terrain": "O",
        "features": "",
        "encounter": ""
    },
    {
        "pos": 9,
        "terrain": "O",
        "features": "",
        "encounter": ""
    },
    {
        "pos": 10,
        "terrain": "O",
        "features": "",
        "encounter": ""
    },
    {
        "pos": 11,
        "terrain": "O",
        "features": "",
        "encounter": ""
    },
    {
        "pos": 12,
        "terrain": "O",
        "features": "Majestic ['Basin']",
        "encounter": ""
    },
    {
        "pos": 13,
        "terrain": "O",
        "features": "Inviting ['Current']",
        "encounter": ""
    },
    {
        "pos": 14,
        "terrain": "O",
        "features": "",
        "encounter": ""
    },
    {
        "pos": 15,
        "terrain": "O",
        "features": "",
        "encounter": ""
    },
    {
        "pos": 16,
        "terrain": "O",
        "features": "",
        "encounter": ""
    },
    {
        "pos": 17,
        "terrain": "O",
        "features": "",
        "encounter": ""
    },
    {
        "pos": 18,
        "terrain": "O",
        "features": "",
        "encounter": ""
    },
    {
        "pos": 19,
        "terrain": "O",
        "features": "",
        "encounter": "A sudden seagulls cawing in the distance breaks the silence, making the nearby bubblegum coral quiver."
    },
    {
        "pos": 20,
        "terrain": "O",
        "features": "",
        "encounter": ""
    },
    {
        "pos": 21,
        "terrain": "O",
        "features": "",
        "encounter": ""
    },
    {
        "pos": 22,
        "terrain": "O",
        "features": "",
        "encounter": ""
    },
    {
        "pos": 23,
        "terrain": "O",
        "features": "",
        "encounter": ""
    },
    {
        "pos": 24,
        "terrain": "O",
        "features": "",
        "encounter": ""
    },
    {
        "pos": 25,
        "terrain": "O",
        "features": "",
        "encounter": ""
    },
    {
        "pos": 26,
        "terrain": "O",
        "features": "",
        "encounter": ""
    },
    {
        "pos": 27,
        "terrain": "O",
        "features": "",
        "encounter": ""
    },
    {
        "pos": 28,
        "terrain": "O",
        "features": "",
        "encounter": ""
    },
    {
        "pos": 29,
        "terrain": "O",
        "features": "",
        "encounter": ""
    },
    {
        "pos": 30,
        "terrain": "O",
        "features": "",
        "encounter": ""
    },
    {
        "pos": 31,
        "terrain": "O",
        "features": "",
        "encounter": ""
    },
    {
        "pos": 32,
        "terrain": "O",
        "features": "",
        "encounter": ""
    },
    {
        "pos": 33,
        "terrain": "O",
        "features": "",
        "encounter": ""
    },
    {
        "pos": 34,
        "terrain": "O",
        "features": "",
        "encounter": ""
    },
    {
        "pos": 35,
        "terrain": "O",
        "features": "Salty ['Basin']",
        "encounter": ""
    },
    {
        "pos": 36,
        "terrain": "O",
        "features": "",
        "encounter": ""
    },
    {
        "pos": 37,
        "terrain": "O",
        "features": "",
        "encounter": ""
    },
    {
        "pos": 38,
        "terrain": "O",
        "features": "Alluring ['Tidal Pool']",
        "encounter": ""
    },
    {
        "pos": 39,
        "terrain": "O",
        "features": "",
        "encounter": ""
    },
    {
        "pos": 40,
        "terrain": "O",
        "features": "",
        "encounter": ""
    },
    {
        "pos": 41,
        "terrain": "O",
        "features": "",
        "encounter": ""
    },
    {
        "pos": 42,
        "terrain": "O",
        "features": "",
        "encounter": ""
    },
    {
        "pos": 43,
        "terrain": "O",
        "features": "",
        "encounter": "A sudden rumbling of a distant underwater volcano breaks the silence, making the nearby hornwort quiver."
    },
    {
        "pos": 44,
        "terrain": "O",
        "features": "",
        "encounter": ""
    },
    {
        "pos": 45,
        "terrain": "O",
        "features": "",
        "encounter": ""
    },
    {
        "pos": 46,
        "terrain": "O",
        "features": "",
        "encounter": ""
    },
    {
        "pos": 47,
        "terrain": "O",
        "features": "Vast ['Whirlpool']",
        "encounter": ""
    },
    {
        "pos": 48,
        "terrain": "O",
        "features": "",
        "encounter": ""
    },
    {
        "pos": 49,
        "terrain": "O",
        "features": "",
        "encounter": ""
    },
    {
        "pos": 50,
        "terrain": "O",
        "features": "",
        "encounter": ""
    },
    {
        "pos": 51,
        "terrain": "O",
        "features": "",
        "encounter": ""
    },
    {
        "pos": 52,
        "terrain": "O",
        "features": "",
        "encounter": ""
    },
    {
        "pos": 53,
        "terrain": "O",
        "features": "",
        "encounter": ""
    },
    {
        "pos": 54,
        "terrain": "O",
        "features": "",
        "encounter": "Your journey leads you to a a deadly, bioluminescent sea creature swarm. As you approach, ghost ships protecting their underwater city from intruders."
    },
    {
        "pos": 55,
        "terrain": "O",
        "features": "",
        "encounter": ""
    },
    {
        "pos": 56,
        "terrain": "O",
        "features": "",
        "encounter": ""
    },
    {
        "pos": 57,
        "terrain": "O",
        "features": "",
        "encounter": ""
    },
    {
        "pos": 58,
        "terrain": "O",
        "features": "",
        "encounter": ""
    },
    {
        "pos": 59,
        "terrain": "O",
        "features": "",
        "encounter": ""
    },
    {
        "pos": 60,
        "terrain": "O",
        "features": "",
        "encounter": ""
    },
    {
        "pos": 61,
        "terrain": "O",
        "features": "Windswept ['Tide']",
        "encounter": ""
    },
    {
        "pos": 62,
        "terrain": "O",
        "features": "",
        "encounter": ""
    },
    {
        "pos": 63,
        "terrain": "O",
        "features": "",
        "encounter": "The presence of a sandbar hiding just below the water's surface makes it difficult to proceed. Perhaps the merfolk nearby can help."
    },
    {
        "pos": 64,
        "terrain": "O",
        "features": "",
        "encounter": ""
    },
    {
        "pos": 65,
        "terrain": "O",
        "features": "",
        "encounter": ""
    },
    {
        "pos": 66,
        "terrain": "O",
        "features": "",
        "encounter": ""
    },
    {
        "pos": 67,
        "terrain": "O",
        "features": "",
        "encounter": ""
    },
    {
        "pos": 68,
        "terrain": "O",
        "features": "",
        "encounter": ""
    },
    {
        "pos": 69,
        "terrain": "O",
        "features": "",
        "encounter": "Blocked by a tidal wave approaching with destructive force, your attention is caught by buzzing of bioluminescent creatures in the depths. Upon investigating, you discover an underwater cave network filled with glowing algae with a pirate flag bearing a fearsome symbol inside."
    },
    {
        "pos": 70,
        "terrain": "O",
        "features": "",
        "encounter": ""
    },
    {
        "pos": 71,
        "terrain": "O",
        "features": "",
        "encounter": ""
    },
    {
        "pos": 72,
        "terrain": "O",
        "features": "",
        "encounter": ""
    },
    {
        "pos": 73,
        "terrain": "O",
        "features": "",
        "encounter": "You uncover the remnants of a ship's broken mast that tell a story of a time when storm giants pursued rescue a group of trapped sailors from a sinking ship.."
    },
    {
        "pos": 74,
        "terrain": "O",
        "features": "",
        "encounter": ""
    },
    {
        "pos": 75,
        "terrain": "O",
        "features": "",
        "encounter": ""
    },
    {
        "pos": 76,
        "terrain": "O",
        "features": "",
        "encounter": ""
    },
    {
        "pos": 77,
        "terrain": "O",
        "features": "",
        "encounter": ""
    },
    {
        "pos": 78,
        "terrain": "O",
        "features": "",
        "encounter": ""
    },
    {
        "pos": 79,
        "terrain": "O",
        "features": "",
        "encounter": ""
    },
    {
        "pos": 80,
        "terrain": "O",
        "features": "",
        "encounter": "The floating seaweed rafts rustles, revealing shipwreck goblins that are performing a ritual to calm a storm."
    },
    {
        "pos": 81,
        "terrain": "O",
        "features": "",
        "encounter": ""
    },
    {
        "pos": 82,
        "terrain": "O",
        "features": "",
        "encounter": ""
    },
    {
        "pos": 83,
        "terrain": "O",
        "features": "",
        "encounter": ""
    },
    {
        "pos": 84,
        "terrain": "O",
        "features": "",
        "encounter": ""
    },
    {
        "pos": 85,
        "terrain": "O",
        "features": "",
        "encounter": ""
    },
    {
        "pos": 86,
        "terrain": "O",
        "features": "",
        "encounter": "You come across a shattered, waterlogged compass of an old campsite, the scent of tangy scent of salt spray still lingering."
    },
    {
        "pos": 87,
        "terrain": "O",
        "features": "",
        "encounter": "The air is filled with the smell of clean, crisp scent of the open sea. You feel a sense of contentment."
    },
    {
        "pos": 88,
        "terrain": "O",
        "features": "",
        "encounter": ""
    },
    {
        "pos": 89,
        "terrain": "O",
        "features": "",
        "encounter": "Every step forward is met with the increasing intensity of aromatic herbs from a coastal garden, suggesting the presence of kraken."
    },
    {
        "pos": 90,
        "terrain": "O",
        "features": "",
        "encounter": ""
    },
    {
        "pos": 91,
        "terrain": "O",
        "features": "",
        "encounter": ""
    },
    {
        "pos": 92,
        "terrain": "O",
        "features": "",
        "encounter": ""
    },
    {
        "pos": 93,
        "terrain": "O",
        "features": "",
        "encounter": ""
    },
    {
        "pos": 94,
        "terrain": "O",
        "features": "",
        "encounter": ""
    },
    {
        "pos": 95,
        "terrain": "O",
        "features": "Luminous ['Atoll']",
        "encounter": ""
    },
    {
        "pos": 96,
        "terrain": "O",
        "features": "",
        "encounter": ""
    },
    {
        "pos": 97,
        "terrain": "O",
        "features": "",
        "encounter": ""
    },
    {
        "pos": 98,
        "terrain": "O",
        "features": "",
        "encounter": "Peering through the dense bubblegum coral, you catch sight of a rare, ancient ship's figurehead. But be cautious, chattering of crabs on a rocky shore suggest crystal reef dwellers are near."
    },
    {
        "pos": 99,
        "terrain": "O",
        "features": "",
        "encounter": ""
    }
]